classification_models_3D/__init__.py
classification_models_3D/__version__.py
classification_models_3D/keras.py
classification_models_3D/kkeras.py
classification_models_3D/models_factory.py
classification_models_3D/tfkeras.py
classification_models_3D/weights.py
classification_models_3D/models/_DepthwiseConv3D.py
classification_models_3D/models/__init__.py
classification_models_3D/models/_common_blocks.py
classification_models_3D/models/convnext.py
classification_models_3D/models/densenet.py
classification_models_3D/models/efficientnet.py
classification_models_3D/models/efficientnet_v2.py
classification_models_3D/models/inception_resnet_v2.py
classification_models_3D/models/inception_v3.py
classification_models_3D/models/mobilenet.py
classification_models_3D/models/mobilenet_v2.py
classification_models_3D/models/resnet.py
classification_models_3D/models/resnext.py
classification_models_3D/models/senet.py
classification_models_3D/models/vgg16.py
classification_models_3D/models/vgg19.py
classification_models_3D-1.1.0.dist-info/LICENSE
classification_models_3D-1.1.0.dist-info/METADATA
classification_models_3D-1.1.0.dist-info/WHEEL
classification_models_3D-1.1.0.dist-info/top_level.txt
classification_models_3D-1.1.0.dist-info/RECORD
