Metadata-Version: 2.1
Name: classification-models-3D
Version: 1.1.0
Summary: Set of models for classification of 3D volumes.
Home-page: https://github.com/ZFTurbo/classification_models_3D
Author: Roman Sol (ZFTurbo)
Author-email: UNKNOWN
License: UNKNOWN
Platform: UNKNOWN
